[
    {
      "anonymous": false,
      "inputs": [
        {
          "indexed": true,
          "internalType": "bytes32",
          "name": "splitId",
          "type": "bytes32"
        },
        {
          "indexed": true,
          "internalType": "address",
          "name": "member",
          "type": "address"
        }
      ],
      "name": "MemberPaid",
      "type": "event"
    },
    {
      "anonymous": false,
      "inputs": [
        {
          "indexed": true,
          "internalType": "bytes32",
          "name": "splitId",
          "type": "bytes32"
        },
        {
          "indexed": true,
          "internalType": "address",
          "name": "initiator",
          "type": "address"
        },
        {
          "indexed": false,
          "internalType": "uint256",
          "name": "totalAmount",
          "type": "uint256"
        }
      ],
      "name": "SplitCreated",
      "type": "event"
    },
    {
      "inputs": [
        {
          "internalType": "uint256",
          "name": "totalAmount",
          "type": "uint256"
        },
        {
          "internalType": "address",
          "name": "initiatorAddress",
          "type": "address"
        },
        {
          "internalType": "uint256",
          "name": "initiatorAmount",
          "type": "uint256"
        },
        {
          "internalType": "address[]",
          "name": "memberAddresses",
          "type": "address[]"
        },
        {
          "internalType": "uint256[]",
          "name": "memberAmounts",
          "type": "uint256[]"
        }
      ],
      "name": "createSplit",
      "outputs": [
        {
          "internalType": "bytes32",
          "name": "",
          "type": "bytes32"
        }
      ],
      "stateMutability": "nonpayable",
      "type": "function"
    },
    {
      "inputs": [
        {
          "internalType": "bytes32",
          "name": "splitId",
          "type": "bytes32"
        }
      ],
      "name": "getSplitDetails",
      "outputs": [
        {
          "internalType": "uint256",
          "name": "totalAmount",
          "type": "uint256"
        },
        {
          "internalType": "address",
          "name": "initiatorAddress",
          "type": "address"
        },
        {
          "internalType": "uint256",
          "name": "initiatorAmount",
          "type": "uint256"
        },
        {
          "internalType": "bool",
          "name": "initiatorPaid",
          "type": "bool"
        },
        {
          "internalType": "address[]",
          "name": "memberAddresses",
          "type": "address[]"
        },
        {
          "internalType": "uint256[]",
          "name": "memberAmounts",
          "type": "uint256[]"
        },
        {
          "internalType": "bool[]",
          "name": "memberPaid",
          "type": "bool[]"
        }
      ],
      "stateMutability": "view",
      "type": "function"
    },
    {
      "inputs": [],
      "name": "globalSplitCount",
      "outputs": [
        {
          "internalType": "uint256",
          "name": "",
          "type": "uint256"
        }
      ],
      "stateMutability": "view",
      "type": "function"
    },
    {
      "inputs": [
        {
          "internalType": "bytes32",
          "name": "splitId",
          "type": "bytes32"
        },
        {
          "internalType": "address",
          "name": "payer",
          "type": "address"
        }
      ],
      "name": "markAsPaid",
      "outputs": [],
      "stateMutability": "nonpayable",
      "type": "function"
    },
    {
      "inputs": [
        {
          "internalType": "bytes32",
          "name": "",
          "type": "bytes32"
        }
      ],
      "name": "splits",
      "outputs": [
        {
          "internalType": "uint256",
          "name": "totalAmount",
          "type": "uint256"
        },
        {
          "components": [
            {
              "internalType": "address",
              "name": "initiatorAddress",
              "type": "address"
            },
            {
              "internalType": "uint256",
              "name": "amount",
              "type": "uint256"
            },
            {
              "internalType": "bool",
              "name": "paid",
              "type": "bool"
            }
          ],
          "internalType": "struct PaymentSplitterRegistry.Initiator",
          "name": "initiator",
          "type": "tuple"
        }
      ],
      "stateMutability": "view",
      "type": "function"
    }
  ]